parchmint/__init__.py
parchmint/benchmarking.py
parchmint/cmdline.py
parchmint/component.py
parchmint/connection.py
parchmint/device.py
parchmint/feature.py
parchmint/layer.py
parchmint/params.py
parchmint/port.py
parchmint/similaritymatcher.py
parchmint/target.py
schemas/parchmint_v1.json
schemas/parchmint_v1_2.json
parchmint-0.3.5.dist-info/LICENSE
parchmint-0.3.5.dist-info/METADATA
parchmint-0.3.5.dist-info/WHEEL
parchmint-0.3.5.dist-info/entry_points.txt
parchmint-0.3.5.dist-info/RECORD
