Metadata-Version: 2.1
Name: parchmint
Version: 0.3.5
Summary: Parchmint is data interchange standard for representing microfluidic designs. Check out https://parchmint.org for more information.
License: BSD-3-Clause
Author: Radhakrishna Sanka
Requires-Python: >=3.8,<3.11
Classifier: License :: OSI Approved :: BSD License
Classifier: Programming Language :: Python :: 3
Classifier: Programming Language :: Python :: 3.8
Classifier: Programming Language :: Python :: 3.9
Classifier: Programming Language :: Python :: 3.10
Provides-Extra: docs
Requires-Dist: argparse (>=1.4.0,<2.0.0)
Requires-Dist: jsonschema (>=3.2.0,<4.0.0)
Requires-Dist: networkx (>=3.0,<4.0)
Requires-Dist: numpy (>=1.22.4,<2.0.0)
Requires-Dist: tabulate (>=0.8.9,<0.9.0)
